MANIFEST.in
README.rst
setup.py
commandRunner/__init__.py
commandRunner/commandRunner.py
commandRunner/geRunner.py
commandRunner/localRunner.py
commandRunner/pythonRunner.py
commandRunner/rRunner.py
commandRunner.egg-info/PKG-INFO
commandRunner.egg-info/SOURCES.txt
commandRunner.egg-info/dependency_links.txt
commandRunner.egg-info/not-zip-safe
commandRunner.egg-info/pbr.json
commandRunner.egg-info/top_level.txt