Metadata-Version: 1.0
Name: commandRunner
Version: 0.8.7
Summary: Allows thread safe, object oriented running of commandline operations and blocks of code
Home-page: https://github.com/AnalyticsAutomated/commandRunner.git
Author: Analytics Automated
Author-email: daniel.buchan@ucl.ac.uk
License: GPL
Platform: UNKNOWN
